fusion/__init__.py
fusion/fusion.py
kernelfusion-0.1.0.dist-info/AUTHORS.rst
kernelfusion-0.1.0.dist-info/LICENSE
kernelfusion-0.1.0.dist-info/METADATA
kernelfusion-0.1.0.dist-info/WHEEL
kernelfusion-0.1.0.dist-info/top_level.txt
kernelfusion-0.1.0.dist-info/RECORD
