Metadata-Version: 2.1
Name: kernelfusion
Version: 0.1.0
Summary: An example kernel fusion Pytorch extension.
Home-page: https://github.com/yngtodd/fusion
Author: Todd Young
Author-email: young.todd.mk@gmail.com
License: BSD license
Keywords: fusion
Platform: UNKNOWN
Classifier: Development Status :: 2 - Pre-Alpha
Classifier: Intended Audience :: Developers
Classifier: License :: OSI Approved :: BSD License
Classifier: Natural Language :: English
Classifier: Programming Language :: Python :: 3.7
